lab8/ex2.v
module ex2 #(parameter N = 8) (
    input clk, input rst, input [N-1:0] d,
    output reg [N-1:0] q
);
    always @(posedge clk or posedge rst) begin
        if (rst)
            q <= {N{1'b0}};
        else
            q <= d;
    end
endmodule

lab8/exx2.v
`timescale 1ns/1ns
`include "ex2.v"

module ex2_tb;
    reg clk, rst;
    reg [7:0] d;
    wire [7:0] q;

    ex2 #(8) uut(clk, rst, d, q);

    initial begin
        clk = 0;
        forever #5 clk = ~clk;
    end

    initial begin
        $dumpfile("ex2.vcd");
        $dumpvars(0, ex2_tb);

        rst = 1; d = 8'h00; #10;
        rst = 0; d = 8'hAA; #10;
        d = 8'h55; #10;
        d = 8'hFF; #10;
        d = 8'h0F; #20;
        $finish;
    end
endmodule

lab8/ex2.vcd
$date
	Tue Oct  7 08:41:33 2025
$end
$version
	Icarus Verilog
$end
$timescale
	1ns
$end
$scope module ex2_tb $end
$var wire 8 ! q [7:0] $end
$var reg 1 " clk $end
$var reg 8 # d [7:0] $end
$var reg 1 $ rst $end
$scope module uut $end
$var wire 1 " clk $end
$var wire 8 % d [7:0] $end
$var wire 1 $ rst $end
$var parameter 32 & N $end
$var reg 8 ' q [7:0] $end
$upscope $end
$upscope $end
$enddefinitions $end
$comment Show the parameter values. $end
$dumpall
b1000 &
$end
#0
$dumpvars
b0 '
b0 %
1$
b0 #
0"
b0 !
$end
#5
1"
#10
0"
b10101010 #
b10101010 %
0$
#15
b10101010 !
b10101010 '
1"
#20
0"
b1010101 #
b1010101 %
#25
b1010101 !
b1010101 '
1"
#30
0"
b11111111 #
b11111111 %
#35
b11111111 !
b11111111 '
1"
#40
0"
b1111 #
b1111 %
#45
b1111 !
b1111 '
1"
