lab6/ex3.v
// 2-to-4 Decoder with active-high enable and active-low outputs
module dec2to4 (
    input en,
    input [1:0] w,
    output reg [3:0] y
);
    always @(*) begin
        if (en) begin
            case (w)
                2'b00: y = 4'b1110;  // only y[0] active (low)
                2'b01: y = 4'b1101;  // only y[1] active
                2'b10: y = 4'b1011;  // only y[2] active
                2'b11: y = 4'b0111;  // only y[3] active
                default: y = 4'b1111;
            endcase
        end else begin
            y = 4'b1111;  // all inactive (high)
        end
    end
endmodule
// 4-to-16 Decoder using four 2-to-4 decoders
module dec4to16 (
    input en,
    input [3:0] w,
    output [15:0] y
);
    wire [3:0] en_lines;
    wire [3:0] y0, y1, y2, y3;

    // First 2-to-4 decoder generates enables for the four blocks
    dec2to4 en_decoder (
        .en(en),
        .w(w[3:2]),
        .y(en_lines)
    );

    // Each block handles 4 outputs
    dec2to4 d0 (.en(~en_lines[0]), .w(w[1:0]), .y(y0));
    dec2to4 d1 (.en(~en_lines[1]), .w(w[1:0]), .y(y1));
    dec2to4 d2 (.en(~en_lines[2]), .w(w[1:0]), .y(y2));
    dec2to4 d3 (.en(~en_lines[3]), .w(w[1:0]), .y(y3));

    assign y = {y3, y2, y1, y0};
endmodule

lab6/tb_decoder3.v
`timescale 1ns/1ps
`include "ex3.v"   // contains dec2to4 and dec4to16

module tb_decoder3;
    reg en;
    reg [3:0] w;
    wire [15:0] y;

    // Instantiate 4-to-16 decoder
    dec4to16 uut (
        .en(en),
        .w(w),
        .y(y)
    );

    integer i;

    initial begin
        // Dumpfile for waveform simulation
        $dumpfile("tb_decoder3.vcd");
        $dumpvars(0, tb_decoder3);

        // Monitor signals
        $monitor("Time=%0t | en=%b | w=%b | y=%b", $time, en, w, y);

        // Disabled case
        en = 0; w = 4'b0000; #10;
        en = 0; w = 4'b1010; #10;

        // Enabled: test all inputs
        en = 1;
        for (i = 0; i < 16; i = i + 1) begin
            w = i;
            #10;
        end

        $finish;
    end
endmodule

lab6/tb_decoder3.vcd
$date
	Tue Sep 23 09:25:44 2025
$end
$version
	Icarus Verilog
$end
$timescale
	1ps
$end
$scope module tb_decoder3 $end
$var wire 16 ! y [15:0] $end
$var reg 1 " en $end
$var reg 4 # w [3:0] $end
$var integer 32 $ i [31:0] $end
$scope module uut $end
$var wire 1 " en $end
$var wire 4 % w [3:0] $end
$var wire 4 & y3 [3:0] $end
$var wire 4 ' y2 [3:0] $end
$var wire 4 ( y1 [3:0] $end
$var wire 4 ) y0 [3:0] $end
$var wire 16 * y [15:0] $end
$var wire 4 + en_lines [3:0] $end
$scope module d0 $end
$var wire 1 , en $end
$var wire 2 - w [1:0] $end
$var reg 4 . y [3:0] $end
$upscope $end
$scope module d1 $end
$var wire 1 / en $end
$var wire 2 0 w [1:0] $end
$var reg 4 1 y [3:0] $end
$upscope $end
$scope module d2 $end
$var wire 1 2 en $end
$var wire 2 3 w [1:0] $end
$var reg 4 4 y [3:0] $end
$upscope $end
$scope module d3 $end
$var wire 1 5 en $end
$var wire 2 6 w [1:0] $end
$var reg 4 7 y [3:0] $end
$upscope $end
$scope module en_decoder $end
$var wire 1 " en $end
$var wire 2 8 w [1:0] $end
$var reg 4 9 y [3:0] $end
$upscope $end
$upscope $end
$upscope $end
$enddefinitions $end
$comment Show the parameter values. $end
$dumpall
$end
#0
$dumpvars
b1111 9
b0 8
b1111 7
b0 6
05
b1111 4
b0 3
02
b1111 1
b0 0
0/
b1111 .
b0 -
0,
b1111 +
b1111111111111111 *
b1111 )
b1111 (
b1111 '
b1111 &
b0 %
bx $
b0 #
0"
b1111111111111111 !
$end
#10000
b10 8
b10 -
b10 0
b10 3
b10 6
b1010 #
b1010 %
#20000
b1110 )
b1110 .
1,
b1111111111111110 !
b1111111111111110 *
b1111 '
b1111 4
02
b0 8
b0 -
b0 0
b0 3
b0 6
b1110 +
b1110 9
b0 #
b0 %
b0 $
1"
#30000
b1111111111111101 !
b1111111111111101 *
b1101 )
b1101 .
b1 -
b1 0
b1 3
b1 6
b1 #
b1 %
b1 $
#40000
b1111111111111011 !
b1111111111111011 *
b1011 )
b1011 .
b10 -
b10 0
b10 3
b10 6
b10 #
b10 %
b10 $
#50000
b1111111111110111 !
b1111111111110111 *
b111 )
b111 .
b11 -
b11 0
b11 3
b11 6
b11 #
b11 %
b11 $
#60000
b1110 (
b1110 1
1/
0,
b1101 +
b1101 9
b1111111111101111 !
b1111111111101111 *
b1111 )
b1111 .
b1 8
b0 -
b0 0
b0 3
b0 6
b100 #
b100 %
b100 $
#70000
b1111111111011111 !
b1111111111011111 *
b1101 (
b1101 1
b1 -
b1 0
b1 3
b1 6
b101 #
b101 %
b101 $
#80000
b1111111110111111 !
b1111111110111111 *
b1011 (
b1011 1
b10 -
b10 0
b10 3
b10 6
b110 #
b110 %
b110 $
#90000
b1111111101111111 !
b1111111101111111 *
b111 (
b111 1
b11 -
b11 0
b11 3
b11 6
b111 #
b111 %
b111 $
#100000
b1110 '
b1110 4
12
0/
b1011 +
b1011 9
b1111111011111111 !
b1111111011111111 *
b1111 (
b1111 1
b10 8
b0 -
b0 0
b0 3
b0 6
b1000 #
b1000 %
b1000 $
#110000
b1111110111111111 !
b1111110111111111 *
b1101 '
b1101 4
b1 -
b1 0
b1 3
b1 6
b1001 #
b1001 %
b1001 $
#120000
b1111101111111111 !
b1111101111111111 *
b1011 '
b1011 4
b10 -
b10 0
b10 3
b10 6
b1010 #
b1010 %
b1010 $
#130000
b1111011111111111 !
b1111011111111111 *
b111 '
b111 4
b11 -
b11 0
b11 3
b11 6
b1011 #
b1011 %
b1011 $
#140000
b1110 &
b1110 7
15
02
b111 +
b111 9
b1110111111111111 !
b1110111111111111 *
b1111 '
b1111 4
b11 8
b0 -
b0 0
b0 3
b0 6
b1100 #
b1100 %
b1100 $
#150000
b1101111111111111 !
b1101111111111111 *
b1101 &
b1101 7
b1 -
b1 0
b1 3
b1 6
b1101 #
b1101 %
b1101 $
#160000
b1011111111111111 !
b1011111111111111 *
b1011 &
b1011 7
b10 -
b10 0
b10 3
b10 6
b1110 #
b1110 %
b1110 $
#170000
b111111111111111 !
b111111111111111 *
b111 &
b111 7
b11 -
b11 0
b11 3
b11 6
b1111 #
b1111 %
b1111 $
#180000
b10000 $
