lab6/ex1.v
module decoder_2to4 (
    input en,
    input [1:0] a,
    output reg [3:0] y
);
    always @(*) begin
        if (en) begin
            if (a == 2'b00) y = 4'b0001;
            else if (a == 2'b01) y = 4'b0010;
            else if (a == 2'b10) y = 4'b0100;
            else if (a == 2'b11) y = 4'b1000;
            else y = 4'b0000;   // default safe case
        end else begin
            y = 4'b0000;        // disabled → all outputs low
        end
    end
endmodule
module decoder_3to8 (
    input en,
    input [2:0] a,
    output [7:0] y
);
    wire [3:0] y0, y1;

    // Lower half (when MSB = 0)
    decoder_2to4 d0 (
        .en(en & ~a[2]),
        .a(a[1:0]),
        .y(y0)
    );

    // Upper half (when MSB = 1)
    decoder_2to4 d1 (
        .en(en & a[2]),
        .a(a[1:0]),
        .y(y1)
    );

    // Combine outputs
    assign y = {y1, y0};
endmodule

lab6/tb_ex1.v
`timescale 1ns/1ps
`include "ex1.v"   // contains decoder_2to4 and decoder_3to8

module tb_ex1;
    reg en;
    reg [2:0] a;
    wire [7:0] y;

    // Instantiate the 3-to-8 decoder
    decoder_3to8 uut (
        .en(en),
        .a(a),
        .y(y)
    );

    initial begin
        // Dumpfile for waveform simulation
        $dumpfile("tb_ex1.vcd");   // creates VCD file
        $dumpvars(0, tb_ex1);      // dump all signals in this module

        // Monitor signals in console
        $monitor("Time=%0t | en=%b | a=%b | y=%b", $time, en, a, y);

        // Initialize
        en = 0; a = 3'b000;
        #10;

        // Enable = 0 → outputs should be 0
        en = 0; a = 3'b101; #10;

        // Enable = 1 → test all input combinations
        en = 1;
        a = 3'b000; #10;
        a = 3'b001; #10;
        a = 3'b010; #10;
        a = 3'b011; #10;
        a = 3'b100; #10;
        a = 3'b101; #10;
        a = 3'b110; #10;
        a = 3'b111; #10;

        // Finish simulation
        $finish;
    end
endmodule

lab6/tb_ex1.vcd
$date
	Tue Sep 23 08:23:11 2025
$end
$version
	Icarus Verilog
$end
$timescale
	1ps
$end
$scope module tb_ex1 $end
$var wire 8 ! y [7:0] $end
$var reg 3 " a [2:0] $end
$var reg 1 # en $end
$scope module uut $end
$var wire 3 $ a [2:0] $end
$var wire 1 # en $end
$var wire 4 % y1 [3:0] $end
$var wire 4 & y0 [3:0] $end
$var wire 8 ' y [7:0] $end
$scope module d0 $end
$var wire 2 ( a [1:0] $end
$var wire 1 ) en $end
$var reg 4 * y [3:0] $end
$upscope $end
$scope module d1 $end
$var wire 2 + a [1:0] $end
$var wire 1 , en $end
$var reg 4 - y [3:0] $end
$upscope $end
$upscope $end
$upscope $end
$enddefinitions $end
$comment Show the parameter values. $end
$dumpall
$end
#0
$dumpvars
b0 -
0,
b0 +
b0 *
0)
b0 (
b0 '
b0 &
b0 %
b0 $
0#
b0 "
b0 !
$end
#10000
b1 (
b1 +
b101 "
b101 $
#20000
b1 &
b1 *
1)
b1 !
b1 '
b0 %
b0 -
b0 (
b0 +
0,
b0 "
b0 $
1#
#30000
b10 !
b10 '
b10 &
b10 *
b1 (
b1 +
b1 "
b1 $
#40000
b100 !
b100 '
b100 &
b100 *
b10 (
b10 +
b10 "
b10 $
#50000
b1000 !
b1000 '
b1000 &
b1000 *
b11 (
b11 +
b11 "
b11 $
#60000
0)
b1 %
b1 -
b10000 !
b10000 '
b0 &
b0 *
1,
b0 (
b0 +
b100 "
b100 $
#70000
b100000 !
b100000 '
b10 %
b10 -
b1 (
b1 +
b101 "
b101 $
#80000
b1000000 !
b1000000 '
b100 %
b100 -
b10 (
b10 +
b110 "
b110 $
#90000
b10000000 !
b10000000 '
b1000 %
b1000 -
b11 (
b11 +
b111 "
b111 $
