lab7/ex1.v
module DFF_async_reset (
    input  wire D,
    input  wire clk,
    input  wire reset, 
    output reg  Q
);
    always @(posedge clk or posedge reset) begin
        if (reset)
            Q <= 1'b0;
        else
            Q <= D;
    end
endmodule

lab7/exx1.v
`timescale 1ns/1ns
`include "ex1.v"

module tb_DFF;
    reg D, clk, reset;
    wire Q;

    DFF_async_reset uut (.D(D), .clk(clk), .reset(reset), .Q(Q));

    initial begin
        clk = 0;
        forever #5 clk = ~clk;
    end

    initial begin
        $dumpfile("dff_waveform.vcd");
        $dumpvars(0, tb_DFF);

        D = 0; reset = 0;
        #2 reset = 1;
        #8 reset = 0;
        #10 D = 1;
        #10 D = 0;
        #10 D = 1;
        #10 D = 0;
        #10 reset = 1;
        #10 reset = 0;
        #20 $finish;
    end
endmodule

lab7/dff_waveform.vcd
$date
	Tue Sep 30 08:32:00 2025
$end
$version
	Icarus Verilog
$end
$timescale
	1ns
$end
$scope module tb_DFF $end
$var wire 1 ! Q $end
$var reg 1 " D $end
$var reg 1 # clk $end
$var reg 1 $ reset $end
$scope module uut $end
$var wire 1 " D $end
$var wire 1 # clk $end
$var wire 1 $ reset $end
$var reg 1 ! Q $end
$upscope $end
$upscope $end
$enddefinitions $end
$comment Show the parameter values. $end
$dumpall
$end
#0
$dumpvars
0$
0#
0"
x!
$end
#2
0!
1$
#5
1#
#10
0#
0$
#15
1#
#20
0#
1"
#25
1!
1#
#30
0#
0"
#35
0!
1#
#40
0#
1"
#45
1!
1#
#50
0#
0"
#55
0!
1#
#60
0#
1$
#65
1#
#70
0#
0$
