lab7/ex2.v
module TFF_async_reset (
    input  wire T,
    input  wire clk,
    input  wire reset_n,
    output reg  Q
);
    always @(negedge clk or negedge reset_n) begin
        if (!reset_n)
            Q <= 1'b0;
        else if (T)
            Q <= ~Q;
    end
endmodule

lab7/exx2.v
`timescale 1ns/1ns
`include "ex2.v"

module tb_TFF;
    reg T, clk, reset_n;
    wire Q;

    TFF_async_reset uut (
        .T(T),
        .clk(clk),
        .reset_n(reset_n),
        .Q(Q)
    );

    initial begin
        clk = 0;
        forever #5 clk = ~clk;
    end

    initial begin
        $dumpfile("tff_waveform.vcd");
        $dumpvars(0, tb_TFF);

        T = 0; reset_n = 0;
        #10 reset_n = 1;
        #10 T = 1;
        #20 T = 0;
        #20 T = 1;
        #20 reset_n = 0;
        #10 reset_n = 1;
        #30 $finish;
    end
endmodule

lab7/tff_waveform.vcd
$date
	Tue Sep 30 08:34:31 2025
$end
$version
	Icarus Verilog
$end
$timescale
	1ns
$end
$scope module tb_TFF $end
$var wire 1 ! Q $end
$var reg 1 " T $end
$var reg 1 # clk $end
$var reg 1 $ reset_n $end
$scope module uut $end
$var wire 1 " T $end
$var wire 1 # clk $end
$var wire 1 $ reset_n $end
$var reg 1 ! Q $end
$upscope $end
$upscope $end
$enddefinitions $end
$comment Show the parameter values. $end
$dumpall
$end
#0
$dumpvars
0$
0#
0"
0!
$end
#5
1#
#10
0#
1$
#15
1#
#20
1!
0#
1"
#25
1#
#30
0!
0#
#35
1#
#40
0#
0"
#45
1#
#50
0#
#55
1#
#60
1!
0#
1"
#65
1#
#70
0!
0#
#75
1#
#80
0#
0$
#85
1#
#90
1!
0#
1$
#95
1#
#100
0!
0#
#105
1#
#110
1!
0#
#115
1#
#120
0!
0#
